nbiot/MMA8452Q.py
nbiot/SDL_Pi_HDC1000.py
nbiot/__init__.py
nbiot/nbiot.py
sixfab_nbiot-1.0.0.dist-info/DESCRIPTION.rst
sixfab_nbiot-1.0.0.dist-info/METADATA
sixfab_nbiot-1.0.0.dist-info/RECORD
sixfab_nbiot-1.0.0.dist-info/WHEEL
sixfab_nbiot-1.0.0.dist-info/dependency_links.txt
sixfab_nbiot-1.0.0.dist-info/metadata.json
sixfab_nbiot-1.0.0.dist-info/top_level.txt
