Metadata-Version: 2.0
Name: sixfab-nbiot
Version: 1.0.0
Summary: sixfab nbiot library for rpi
Home-page: https://github.com/sixfab/Sixfab_RPi_NBIoT_Library
Author: Yasin Kaya
Author-email: yasinkaya.121@gmail.com
License: MIT
Platform: UNKNOWN
Requires-Dist: Adafruit-GPIO (>=0.9.3)
Requires-Dist: adafruit-ads1x15
Requires-Dist: pyserial
